engrate_kit/__init__.py
engrate_kit/cli.py
engrate_kit/core/__init__.py
engrate_kit/core/app.py
engrate_kit/core/conf.py
engrate_kit/core/db.py
engrate_kit/core/lifespan.py
engrate_kit/core/logging.py
engrate_kit/core/mcp.py
engrate_kit/templates/.dockerignore
engrate_kit/templates/.gitignore
engrate_kit/templates/Dockerfile
engrate_kit/templates/README.md
engrate_kit/templates/alembic.ini
engrate_kit/templates/main.py
engrate_kit/templates/plugin_manifest.yaml
engrate_kit/templates/pyproject.toml
engrate_kit/templates/migrations/env.py
engrate_kit/templates/migrations/script.py.mako
engrate_kit/templates/migrations/versions/placeholder.txt
engrate_kit/templates/src/{{app_module_name}}/__init__.py
engrate_kit/templates/src/{{app_module_name}}/app.py
engrate_kit/templates/src/{{app_module_name}}/conf.py
engrate_kit/templates/src/{{app_module_name}}/mcp/__init__.py
engrate_kit/templates/src/{{app_module_name}}/mcp/health_server.py
engrate_kit/templates/src/{{app_module_name}}/models/__init__.py
engrate_kit/templates/src/{{app_module_name}}/routers/__init__.py
engrate_kit/templates/src/{{app_module_name}}/routers/health_router.py
engrate_kit/templates/src/{{app_module_name}}/schemas/__init__.py
engrate_kit/templates/tests/conftest.py
engrate_kit/templates/tests/test_health_endpoints.py
engrate_kit/templates/tests/test_health_mcp.py
engrate_kit/testing/__init__.py
engrate_kit/testing/fixtures.py
engrate_kit/utils/__init__.py
engrate_kit/utils/alembic.py
engrate_kit/utils/devdb.py
engrate_kit/utils/plugin.py
engrate_kit/utils/templating.py
engrate_kit-0.0.17.dist-info/METADATA
engrate_kit-0.0.17.dist-info/WHEEL
engrate_kit-0.0.17.dist-info/entry_points.txt
engrate_kit-0.0.17.dist-info/RECORD
