Metadata-Version: 2.4
Name: engrate-kit
Version: 0.0.17
Summary: Development toolkit to quickly build Engrate plugins.
Requires-Python: >=3.12
Requires-Dist: aiosqlite>=0.21.0
Requires-Dist: alembic>=1.16.5
Requires-Dist: fastapi[standard]>=0.118.3
Requires-Dist: fastmcp>=2.12.4
Requires-Dist: sqlmodel>=0.0.27
Requires-Dist: structlog>=25.4.0
Requires-Dist: tomli-w>=1.2.0
